csv_sqlite_converter/__init__.py
csv_sqlite_converter/__main__.py
csv_sqlite_converter/context_managers/__init__.py
csv_sqlite_converter/context_managers/csv_managers.py
csv_sqlite_converter/context_managers/db_manager.py
csv_sqlite_converter/csv_to_sqlite/__init__.py
csv_sqlite_converter/csv_to_sqlite/input_checks.py
csv_sqlite_converter/csv_to_sqlite/transfer_data_from_csv_to_sqlite.py
csv_sqlite_converter/sqlite_to_csv/__init__.py
csv_sqlite_converter/sqlite_to_csv/transfer_data_from_sqlite_to_csv.py
csv_sqlite_converter/validation/__init__.py
csv_sqlite_converter/validation/db_input_validation.py
csv_sqlite_converter-0.0.1.dist-info/LICENSE.txt
csv_sqlite_converter-0.0.1.dist-info/METADATA
csv_sqlite_converter-0.0.1.dist-info/WHEEL
csv_sqlite_converter-0.0.1.dist-info/entry_points.txt
csv_sqlite_converter-0.0.1.dist-info/top_level.txt
csv_sqlite_converter-0.0.1.dist-info/RECORD
