Metadata-Version: 2.1
Name: csv-sqlite-converter
Version: 0.0.1
Summary: A convenient tool for transferring files between SQLite database and csv files and vice versa.
Author-email: undeMalum <polakwmc@gazeta.pl>
Project-URL: repository, https://github.com/undeMalum/csv-sqlite-converter
Keywords: csv,sqlite,converter
Classifier: License :: OSI Approved :: MIT License
Classifier: Programming Language :: Python
Classifier: Programming Language :: Python :: 3
Requires-Python: >=3.10
License-File: LICENSE.txt
Provides-Extra: build
Requires-Dist: build ; extra == 'build'
Requires-Dist: twine ; extra == 'build'
Provides-Extra: dev
Requires-Dist: pytest ; extra == 'dev'
